{"numero":"85","stations":[{"id":"85190001","commune":"AIZENAY","cp":"85190","adresse":"Espace commercial porte du littoral - bp 10","nom":"Hyper U AIZENAY","marque":"Systeme U"},{"id":"85190004","commune":"AIZENAY","cp":"85190","adresse":"7 route de saint-gilles","nom":"INTERMARCHE AIZENAY","marque":"Intermarche"},{"id":"85190002","commune":"AIZENAY","cp":"85190","adresse":"Route de la roche","nom":"SARL GARAGE NEAU","marque":"TotalEnergies"},{"id":"85750002","commune":"ANGLES","cp":"85750","adresse":"Lieu-dit la dugeonniere","nom":"INTERMARCHE  ANGLES","marque":"Intermarche Contact"},{"id":"85120002","commune":"ANTIGNY","cp":"85120","adresse":"Z.i. de la levraudiere","nom":"PICOTY OUEST - ANTIGNY","marque":"Avia"},{"id":"85630001","commune":"BARBATRE","cp":"85630","adresse":"Rue de la cure","nom":"U EXPRESS BARBATRE","marque":"Systeme U"},{"id":"85230003","commune":"BEAUVOIR-SUR-MER","cp":"85230","adresse":"39 rue de la roche","nom":"INTERMARCHE BEAUVOIR SUR MER","marque":"Intermarche"},{"id":"85230001","commune":"BEAUVOIR-SUR-MER","cp":"85230","adresse":"Route des sables","nom":"Super U BEAUVOIR SUR MER","marque":"Systeme U"},{"id":"85170005","commune":"BELLEVIGNY","cp":"85170","adresse":"1 rue de l'epine","nom":"AUTO BELLEVIGNY TOTAL","marque":"TotalEnergies"},{"id":"85170003","commune":"BELLEVIGNY","cp":"85170","adresse":"Route de nantes","nom":"STATION AVIA BRETECHE","marque":"AVIA"},{"id":"85170001","commune":"BELLEVILLE-SUR-VIE","cp":"85170","adresse":"Boulevard de la vie","nom":"Super U BELLEVILLE SUR VIE","marque":"Systeme U"},{"id":"85490001","commune":"BENET","cp":"85490","adresse":"2 rue de la gare","nom":"INTERMARCHE BENET","marque":"Intermarche"},{"id":"85600003","commune":"BOUFFERE","cp":"85600","adresse":"Rond point porte de bouffere","nom":"Super U PAYS DE MONTAIGU","marque":"Systeme U"},{"id":"85480001","commune":"BOURNEZEAU","cp":"85480","adresse":"58 avenue du moulin","nom":"10","marque":"TotalEnergies"},{"id":"85470002","commune":"BRETIGNOLLES-SUR-MER","cp":"85470","adresse":" avenue de verdun","nom":"Super U BRETIGNOLLES","marque":"Systeme U"},{"id":"85300002","commune":"CHALLANS","cp":"85300","adresse":"Route de noirmoutier","nom":"Centre E.Leclerc","marque":"Leclerc"},{"id":"85306001","commune":"CHALLANS","cp":"85300","adresse":"Boulevard jean xxiii","nom":"Hyper U CHALLANS","marque":"Systeme U"},{"id":"85300004","commune":"CHALLANS","cp":"85300","adresse":"Rue st francois","nom":"INTERMARCHE CHALLANS CEDEX","marque":"Intermarche"},{"id":"85300001","commune":"CHALLANS","cp":"85300","adresse":"3 boulevard des f.f.i.","nom":"SARL GGE PONTOIZEAU","marque":"TotalEnergies"},{"id":"85300006","commune":"CHALLANS","cp":"85300","adresse":"Route de cholet","nom":"Station Esso Challans","marque":"Esso"},{"id":"85110006","commune":"CHANTONNAY","cp":"85110","adresse":"Parc activite polaris nord","nom":"E.LECLERC CHANTONNAY","marque":"Leclerc"},{"id":"85110005","commune":"CHANTONNAY","cp":"85110","adresse":"42 avenue monseigneur batiot","nom":"Garage de la mozee","marque":"TotalEnergies"},{"id":"85110001","commune":"CHANTONNAY","cp":"85110","adresse":"45,  av  g.  clemenceau","nom":"Hyper U CHANTONNAY","marque":"Systeme U"},{"id":"85130002","commune":"CHANVERRIE","cp":"85130","adresse":"6 rue blaise pascal la verrie","nom":"GARAGE LES 3 COURONNES ( agent FORD)","marque":"TotalEnergies"},{"id":"85180003","commune":"CHATEAU-D'OLONNE","cp":"85180","adresse":"Rue des plesses","nom":"INTERMARCHE CHATEAU D'OLONNE","marque":"Intermarche"},{"id":"85100002","commune":"CHATEAU-D'OLONNE","cp":"85180","adresse":"Rue du bocage","nom":"SARL GGE RAVON","marque":"TotalEnergies"},{"id":"85250003","commune":"CHAVAGNES EN PAILLERS","cp":"85250","adresse":"Autoroute a83aire de chavagnes en paillers","nom":"DYNEFF AIRE DE CHAVAGNES EN PAILLERS","marque":"Dyneff"},{"id":"85220002","commune":"COEX","cp":"85220","adresse":"Les petits trais-rd ndeg6","nom":"SAS SOCODI","marque":"Systeme U"},{"id":"85670002","commune":"FALLERON","cp":"85670","adresse":"8 rue nationale","nom":"SARL GARAGE TENAILLEAU","marque":"ESSO"},{"id":"85200001","commune":"FONTENAY-LE-COMTE","cp":"85200","adresse":"Route de la rochelle","nom":"Hyper U FONTENAY LE COMTE","marque":"Systeme U"},{"id":"85200005","commune":"FONTENAY-LE-COMTE","cp":"85200","adresse":"Avenue du president francois mitterrand","nom":"Station de Fontenay 2","marque":"Leclerc"},{"id":"85202001","commune":"FONTENAY-LE-COMTE","cp":"85200","adresse":"Avenue du general de gaulle","nom":"SUD-VENDEE-DISTRIBUTION","marque":"Leclerc"},{"id":"85200004","commune":"FONTENAY-LE-COMTE","cp":"85200","adresse":"26 bd du bas poitou","nom":"TOTAL CONTACT FONTENAY LE COMTE","marque":"Elan"},{"id":"85520001","commune":"JARD-SUR-MER","cp":"85520","adresse":"2 a rue de la perpoise","nom":"Super U JARD SUR MER","marque":"Systeme U"},{"id":"85550001","commune":"LA BARRE-DE-MONTS","cp":"85550","adresse":"Avenue de l'estacade bp 4","nom":"INTERMARCHE FROMENTINE","marque":"Intermarche"},{"id":"85530003","commune":"LA BRUFFIERE","cp":"85530","adresse":"2 rue andre defontaine","nom":"Sarl Bruffiere Automobiles","marque":"Elan"},{"id":"85530001","commune":"LA BRUFFIERE","cp":"85530","adresse":"Rue de la brulerie","nom":"Super U LA BRUFFIERE","marque":"Systeme U"},{"id":"85310001","commune":"LA CHAIZE-LE-VICOMTE","cp":"85310","adresse":"31 rue du  moulin rouge","nom":"SARL GARAGE DU MOULIN ROUGE","marque":"Avia"},{"id":"85150003","commune":"LA CHAPELLE-ACHARD","cp":"85150","adresse":"Za sud","nom":"STATION DES ACHARDS","marque":"Avia"},{"id":"85120005","commune":"LA CHATAIGNERAIE","cp":"85120","adresse":"7 rue de la garenne","nom":"INTERMARCHE LA CHATAIGNERAIE","marque":"Intermarche"},{"id":"85120001","commune":"LA CHATAIGNERAIE","cp":"85120","adresse":"52 avenue du general de gaulle","nom":"Super U LA CHATAIGNERAIE","marque":"Systeme U"},{"id":"85280002","commune":"LA FERRIERE","cp":"85280","adresse":"Rue nationale","nom":"RAVIR / station TOTAL","marque":"TotalEnergies"},{"id":"85710002","commune":"LA GARNACHE","cp":"85710","adresse":"Rue du chemin bas","nom":"SARL LO' NA","marque":"Systeme U"},{"id":"85130006","commune":"LA GAUBRETIERE","cp":"85130","adresse":"15 rue pierre rangeard","nom":"SUPERMARCHE UTILE","marque":"Systeme U"},{"id":"85130007","commune":"LA GAUBRETIERE","cp":"85130","adresse":"4 rue des alouettes","nom":"TOTAL LA GAUBRETIERE","marque":"TotalEnergies"},{"id":"85460003","commune":"L'AIGUILLON-SUR-MER","cp":"85460","adresse":"Route de saint-michel-en-l'herm","nom":"Super U L'AIGUILLON SUR MER","marque":"Systeme U"},{"id":"85000002","commune":"LA ROCHE-SUR-YON","cp":"85000","adresse":"5 rue des platanes","nom":"CARREFOUR LA ROCHE SUR YON","marque":"Carrefour"},{"id":"85000007","commune":"LA ROCHE-SUR-YON","cp":"85000","adresse":"Rue newton","nom":"E.LECLERC LES OUDAIRIES","marque":"Leclerc"},{"id":"85000010","commune":"LA ROCHE-SUR-YON","cp":"85000","adresse":"44 route de nantes","nom":"ESSO LA ROCHE SUR YON","marque":"Esso"},{"id":"85000001","commune":"LA ROCHE-SUR-YON","cp":"85000","adresse":"Route de nantes","nom":"Hyper U Coop Atlantique La Roche/Yon","marque":"Systeme U"},{"id":"85000009","commune":"LA ROCHE-SUR-YON","cp":"85000","adresse":"Boulevard edison","nom":"INTERMARCHE LA ROCHE SUR YON","marque":"Intermarche"},{"id":"85000004","commune":"LA ROCHE-SUR-YON","cp":"85000","adresse":"Rue savary de l'epineraye","nom":"SARL GARAGE PHELIPPEAU","marque":"TotalEnergies"},{"id":"85000008","commune":"LA ROCHE-SUR-YON","cp":"85000","adresse":"Rte de la tranche","nom":"STATION E. LECLERC-SODIROCHE","marque":"Leclerc"},{"id":"85000003","commune":"LA ROCHE-SUR-YON","cp":"85000","adresse":"Boulevard stephane moreau","nom":"Super U LA ROCHE SUR YON","marque":"Systeme U"},{"id":"85360001","commune":"LA TRANCHE-SUR-MER","cp":"85360","adresse":"Chemin du vasais de millet","nom":"Super U LA TRANCHE SUR MER","marque":"Systeme U"},{"id":"85130005","commune":"LA VERRIE","cp":"85130","adresse":"10 rue des ecoles","nom":"SUPERMARCHE UTILE","marque":"Systeme U"},{"id":"85510001","commune":"LE BOUPERE","cp":"85510","adresse":"Rue eugene charrier","nom":"ECOMARCHE LE BOUPERE","marque":"Intermarche"},{"id":"85540003","commune":"LE CHAMP-SAINT-PERE","cp":"85540","adresse":"Rue des tourterelles","nom":"Carrefour Contact","marque":"Carrefour Contact"},{"id":"85260007","commune":"LE MARCHAS-CLAVEAU","cp":"85260","adresse":"Autoroute a83aire des brouzils","nom":"DYNEFF AIRE DES BROUZILS","marque":"Dyneff"},{"id":"85170009","commune":"LE POIRE SUR VIE","cp":"85170","adresse":"2 rue de la brachetiere","nom":"NETTO-SAS NALYNY","marque":"Netto"},{"id":"85170006","commune":"LE POIRE-SUR-VIE","cp":"85170","adresse":"48 bd des deux moulins","nom":"LECLERC PSV","marque":"Leclerc"},{"id":"85150001","commune":"LES ACHARDS","cp":"85150","adresse":"1 rue des bles, la mothe achard","nom":"Super U LA MOTHE ACHARD","marque":"Systeme U"},{"id":"85260005","commune":"LES BROUZILS","cp":"85260","adresse":"1 za la colonne 1","nom":"R SERVICES - AMIAUD","marque":"R SERVICES"},{"id":"85590001","commune":"LES EPESSES","cp":"85590","adresse":"Rue pierre de coubertin","nom":"INTERMARCHE LES EPESSES","marque":"Intermarche Contact"},{"id":"85140001","commune":"LES ESSARTS","cp":"85140","adresse":"Cc   les charmettes","nom":"Super U LES ESSARTS","marque":"Systeme U"},{"id":"85500005","commune":"LES HERBIERS","cp":"85500","adresse":"Avenue des chauvieres","nom":"HERBIDIS","marque":"Leclerc"},{"id":"85500002","commune":"LES HERBIERS","cp":"85500","adresse":"Avenue de la maine","nom":"Hyper U LES HERBIERS","marque":"Systeme U"},{"id":"85500001","commune":"LES HERBIERS","cp":"85500","adresse":"A87 aire des herbiers","nom":"ROMPETROL Les Herbiers","marque":"DYNEFF"},{"id":"85500003","commune":"LES HERBIERS","cp":"85500","adresse":"40, ave georges clemenceau","nom":"SAS GARAGE MARTINEAU","marque":"TotalEnergies"},{"id":"85170008","commune":"LES LUCS SUR BOULOGNE","cp":"85170","adresse":"Rond point de la vendee","nom":"CARREFOUR CONTACT","marque":"Carrefour Contact"},{"id":"85180004","commune":"LES SABLES D'OLONNE","cp":"85180","adresse":"15 rue du general montcalm le chateau d'olonne","nom":"Super U Chateau d'Olonne","marque":"Systeme U"},{"id":"85100001","commune":"LES SABLES-D'OLONNE","cp":"85100","adresse":"Rue la petite garliere","nom":"Carrefour Market","marque":"Carrefour Market"},{"id":"85100003","commune":"LES SABLES-D'OLONNE","cp":"85100","adresse":"33 avenue d'aquitaine","nom":"SA MAISON RABREAU","marque":"TotalEnergies"},{"id":"85100004","commune":"LES SABLES-D'OLONNE","cp":"85100","adresse":"68 rue joseph benatier","nom":"Super U LA CHAUME","marque":"Systeme U"},{"id":"85350001","commune":"L'ILE-D'YEU","cp":"85350","adresse":"9 rue neptune","nom":"Sarl Martin Cantin","marque":"Independant sans enseigne"},{"id":"85140004","commune":"L'OIE","cp":"85140","adresse":"56 rue nationale","nom":"Le Relais de l'Oie","marque":"TotalEnergies"},{"id":"85560004","commune":"LONGEVILLE-SUR-MER","cp":"85560","adresse":"23 rue georges clemenceau","nom":"INTERMARCHE LONGEVILLE SUR MER","marque":"Intermarche"},{"id":"85560001","commune":"LONGEVILLE-SUR-MER","cp":"85560","adresse":"322 rue de l'ocean","nom":"STATION GARAGE DE L'OCEAN","marque":"TotalEnergies"},{"id":"85403001","commune":"LUCON","cp":"85400","adresse":"Chemin des roches","nom":"Chemin des Roches","marque":"Leclerc"},{"id":"85400005","commune":"LUCON","cp":"85400","adresse":"2 route de fontenay","nom":"Magasin La Belle Vie","marque":"Leclerc"},{"id":"85400006","commune":"LUCON","cp":"85400","adresse":"97 rue du president de gaulle","nom":"SAS LUCON DISTRIBUTION","marque":"Intermarche"},{"id":"85400001","commune":"LUCON","cp":"85400","adresse":"Bd michel phelippon","nom":"Super U LUCON","marque":"Systeme U"},{"id":"85190003","commune":"MACHE","cp":"85190","adresse":"Bel air","nom":"STATION AVIA","marque":"Avia"},{"id":"85320002","commune":"MAREUIL-SUR-LAY-DISSAIS","cp":"85320","adresse":"2, rue des acacias","nom":"INTERMARCHE MAREUIL SUR LAY","marque":"Intermarche"},{"id":"85603001","commune":"MONTAIGU","cp":"85600","adresse":"Rue amiral duchaffault","nom":"SODINOVE","marque":"Leclerc"},{"id":"85290006","commune":"MORTAGNE-SUR-SEVRE","cp":"85290","adresse":"Route de cholet","nom":"Super U MORTAGNE SUR SEVRE","marque":"Systeme U"},{"id":"85640001","commune":"MOUCHAMPS","cp":"85640","adresse":"Rue de la ville en bois","nom":"STATION ESSO GARAGE VILLENEUVE","marque":"Esso"},{"id":"85000012","commune":"MOUILLERON-LE-CAPTIF","cp":"85000","adresse":"208 rue du clair bocage","nom":"RELAIS DU BALMORAL","marque":"TotalEnergies Access"},{"id":"85540002","commune":"MOUTIERS-LES-MAUXFAITS","cp":"85540","adresse":"Avenue georges clemenceau","nom":"INTERMARCHE MOUTIERS LES MAUXFAI","marque":"Intermarche Contact"},{"id":"85430001","commune":"NIEUL-LE-DOLENT","cp":"85430","adresse":"Impasse bellevue","nom":"U Express  NIEUL LE DOLENT","marque":"Systeme U"},{"id":"85330003","commune":"NOIRMOUTIER-EN-L'ILE","cp":"85330","adresse":"148, route nationale","nom":"Super U NOIRMOUTIER","marque":"Systeme U"},{"id":"85680001","commune":"NOIRMOUTIER, LA GUERINIERE","cp":"85680","adresse":"Route de noirmoutier","nom":"INTERMARCHE LA GUERINIERE","marque":"Intermarche"},{"id":"85690001","commune":"NOTRE-DAME-DE-MONTS","cp":"85690","adresse":"Route du fief noumois","nom":"U Express NOTRE DAME DE MONTS","marque":"Systeme U"},{"id":"85340001","commune":"OLONNE SUR MER","cp":"85340","adresse":"73 rue du 8 mai 1945","nom":"Super U Olonne Sur Mer","marque":"Systeme U"},{"id":"85340002","commune":"OLONNE-SUR-MER","cp":"85340","adresse":"144 avenue francois mitterrand","nom":"RELAIS OLIVIER TESSON","marque":"TotalEnergies"},{"id":"85340003","commune":"OLONNE-SUR-MER","cp":"85340","adresse":"87 avenue francois mitterand","nom":"S.A.S. SODILONNE","marque":"Leclerc"},{"id":"85700002","commune":"POUZAUGES","cp":"85700","adresse":"35 rue charles largeteau","nom":"SARL MCN DISTRIBUTION","marque":"Systeme U"},{"id":"85310002","commune":"RIVES DE L'YON","cp":"85310","adresse":"36 rue petit moineau","nom":"GUERINEAU","marque":"TotalEnergies"},{"id":"85620001","commune":"ROCHESERVIERE","cp":"85620","adresse":"Route de vieillevigne","nom":"INTERMARCHE ROCHESERVIERE","marque":"Intermarche"},{"id":"85400008","commune":"SAINTE-GEMME-LA-PLAINE","cp":"85400","adresse":"Les quatre chemins","nom":"Le Fournil Vendeen","marque":"TotalEnergies"},{"id":"85210010","commune":"SAINTE HERMINE","cp":"85210","adresse":"132 route de nantes","nom":"Intermarche SAINTE HERMINE","marque":"Intermarche"},{"id":"85210007","commune":"SAINTE-HERMINE","cp":"85210","adresse":"A 83 aire de la vendee","nom":"SARL LES HARAS","marque":"Avia"},{"id":"85250001","commune":"SAINT-FULGENT","cp":"85250","adresse":"Avenue de la metairie","nom":"Super U ST FULGENT","marque":"Systeme U"},{"id":"85600005","commune":"SAINT-GEORGES-DE-MONTAIGU","cp":"85600","adresse":"89 rue durivum","nom":"AVIA - MJ BELETEAU","marque":"Avia"},{"id":"85800003","commune":"SAINT-GILLES-CROIX-DE-VIE","cp":"85800","adresse":"Rd pt de l'europe  parc oceanis","nom":"SAINT GILLES SUD","marque":"Leclerc"},{"id":"85800002","commune":"SAINT-GILLES-CROIX-DE-VIE","cp":"85800","adresse":"Les marattes cd 38 bis","nom":"SARL RELAIS DES SALINES","marque":"TotalEnergies"},{"id":"85804001","commune":"SAINT-GILLES-CROIX-DE-VIE","cp":"85800","adresse":"1 rue de la drie","nom":"SAS S.G.D.","marque":"Systeme U"},{"id":"85600001","commune":"SAINT-HILAIRE-DE-LOULAY","cp":"85600","adresse":"11 rue de la vendee","nom":"GARAGE CHARRIER","marque":"TOTAL"},{"id":"85600002","commune":"SAINT-HILAIRE-DE-LOULAY","cp":"85600","adresse":"Route de cholet","nom":"INTERMARCHE MONTAIGU","marque":"Intermarche"},{"id":"85270001","commune":"SAINT-HILAIRE-DE-RIEZ","cp":"85270","adresse":"Avenue du terre fort  face hyper u","nom":"Hyper U ST HILAIRE DE RIEZ","marque":"Systeme U"},{"id":"85210009","commune":"SAINT-JEAN-DE-BEUGNE","cp":"85210","adresse":"72 route nationale 137","nom":"LEX'PER AUTO","marque":"TotalEnergies"},{"id":"85160006","commune":"SAINT-JEAN-DE-MONTS","cp":"85160","adresse":"Rue de la riviere","nom":"intermarche","marque":"Intermarche"},{"id":"85160005","commune":"SAINT-JEAN-DE-MONTS","cp":"85160","adresse":"Route de challans","nom":"Super U  ST JEAN DE MONTS","marque":"Systeme U"},{"id":"85290010","commune":"SAINT-LAURENT-SUR-SEVRE","cp":"85290","adresse":"1 rue des martyrs","nom":"CARREFOUR CONTACT SAINT LAURENT SUR SEVRE","marque":"Carrefour Contact"},{"id":"85290004","commune":"SAINT-LAURENT-SUR-SEVRE","cp":"85290","adresse":"Rn 149 la trique","nom":"FUSELIEZ","marque":"TotalEnergies"},{"id":"85440002","commune":"TALMONT-SAINT-HILAIRE","cp":"85440","adresse":"91 avenue des sables","nom":"SARL THOMAS AUTOMOBILES","marque":"TotalEnergies"},{"id":"85440001","commune":"TALMONT-SAINT-HILAIRE","cp":"85440","adresse":"86 avenue des sables","nom":"Super U TALMONT ST HILAIRE","marque":"Systeme U"},{"id":"85530002","commune":"TREIZE-SEPTIERS","cp":"85600","adresse":"Rn 753 - route de montaigu","nom":"SARL AUTOMOBILES VENDEE SERVICES","marque":"TotalEnergies"}]}